[
	   {
		"question": "François I<sup>er</sup> était réputé pour être :",
		"question_img": "none",
		"proposition_a": "Petit",
		"proposition_b": "Galant",
		"proposition_c": "Sportif",
		"bonne_reponse": "b",
		"reponse": "none",
		"reponse_anim": "none"
	},
	{
		"question": "Pendant quelle période François I<sup>er</sup> a-t-il été Roi ?",
		"question_img": "none",
		"proposition_a": "La Révolution Française",
		"proposition_b": "Le Moyen Âge",
		"proposition_c": "La Renaissance",
		"bonne_reponse": "c",
		"reponse": "none",
		"reponse_anim": "none"
	},
	{
		"question": "François I<sup>er</sup> est souvent utilisé par la publicité pour :",
		"question_img": "none",
		"proposition_a": "Vanter des bicyclettes",
		"proposition_b": "Vanter des alcools raffinés",
		"proposition_c": "Vanter des chapeaux",
		"bonne_reponse": "b",
		"reponse": "none",
		"reponse_anim": "Q13_Franc_1er.webm"
	},
	{
		"question": "On dit d'Henri IV qu'il était :",
		"question_img": "none",
		"proposition_a": "Injuste avec son peuple",
		"proposition_b": "Proche de son peuple",
		"proposition_c": "Cruel avec son peuple",
		"bonne_reponse": "b",
		"reponse": "none",
		"reponse_anim": "none"
	},
	{
		"question": "<span style='font-size:0.95em'>Qu'est-ce qu'Henri IV voulait donner à manger aux français ?</span>",
		"question_img": "none",
		"proposition_a": "Un bœuf bourguignon",
		"proposition_b": "Une poule au pot",
		"proposition_c": "Un pot au feu",
		"bonne_reponse": "b",
		"reponse": "<span  class='reponse_100pc'>« Si Dieu me donne encore de la vie<br> je ferai qu’il n’y aura point de laboureur en mon Royaume<br> qui n’ait moyen d’avoir une poule dans son pot.»<br><br>Citation communément attribuée à Henri IV  </span>",
		"reponse_anim": "none"
	},
	{
		"question": "Qui a vécu à Versailles ?",
		"question_img": "none",
		"proposition_a": "Henri XIV",
		"proposition_b": "Louis XIV",
		"proposition_c": "François I<sup>er</sup>",
		"bonne_reponse": "b",
		"reponse": "none",
		"reponse_anim": "none"
	},
	{
		"question": "Quel était le symbole de Louis XIV ?",
		"question_img": "none",
		"proposition_a": "Un glaive",
		"proposition_b": "Le lion",
		"proposition_c": "Le soleil",
		"bonne_reponse": "c",
		"reponse": "none",
		"reponse_anim": "Q17_louis XIV.webm"
	},
	{
		"question": "Au temps de Louis XIV, Versailles était un château :",
		"question_img": "none",
		"proposition_a": "Tout petit",
		"proposition_b": "Très inconfortable et froid",
		"proposition_c": "Situé dans le Sud de la France",
		"bonne_reponse": "b",
		"reponse": "none",
		"reponse_anim": "none"
	},
	{
		"question": "Comment appelait-on ces personnages de la Révolution Française ?",
		"question_img": "none",
		"proposition_a": "Les sans-culottes",
		"proposition_b": "Les culottes rayées",
		"proposition_c": "Les culottes rouges",
		"bonne_reponse": "a",
		"reponse": "<span class='reponse_100pc'>En 1789, l’on nomme  - non sans mépris - « sans-culottes »<br> les manifestants populaires qui portent des pantalons<br> au lieu des « culottes » avec bas réservées<br> aux nobles et aux bourgeois.</span>",
		"reponse_anim": "none"
	},
	{
		"question": "Quel évènement de la Révolution Française est célébré le 14 Juillet ?",
		"question_img": "none",
		"proposition_a": "La mort de Louis XVI",
		"proposition_b": "La prise de la Bastille",
		"proposition_c": "La proclamation de la République",
		"bonne_reponse": "b",
		"reponse": "none",
		"reponse_anim": "none"
	}
]
